Workbook

Sheet START_HERE
A1: LMS Feature Selection Checklist
A2: Purpose | B2: Select which features should stay in the final LMS.
A3: How to use | B3: Use Decision dropdown: YES / NO / MAYBE. Use Notes for custom changes.
A4: USER | B4: User-facing features and User commands.
A5: ADMIN | B5: Admin-only features and Admin commands.
A6: SECURITY | B6: Vercel, backend, privacy, recovery and protection.
A7: AI | B7: AI response and portal-specific behavior.
A8: MASTER | B8: All features combined in one checklist.
A9: Deployment | B9: Real BOT_TOKEN/API keys/encryption keys must remain Vercel Environment Variables.

Sheet USER
A1: Tick | B1: ID | C1: Role | D1: Command / Code | E1: Feature / Requirement | F1: Decision | G1: Notes | I1: TABLET CONTROL | J1: HOW TO USE
A2: ✅ YES | B2: U01 | C2: USER | D2: /start | E2: Welcome/menu open | F2: =IF(A2="✅ YES","YES",IF(A2="❌ NO","NO",IF(A2="🟨 MAYBE","MAYBE",""))) -> YES | I2: 1 | J2: Tap TICK cell
A3: ✅ YES | B3: U02 | C3: USER | D3: /start ref_ID | E3: Referral/deep-link tracking | F3: =IF(A3="✅ YES","YES",IF(A3="❌ NO","NO",IF(A3="🟨 MAYBE","MAYBE",""))) -> YES | I3: 2 | J3: Choose ✅ YES / ❌ NO / 🟨 MAYBE
A4: ✅ YES | B4: U03 | C4: USER | D4: BACKUP_CHANNEL_CHECK | E4: Backup-channel / join verification gate | F4: =IF(A4="✅ YES","YES",IF(A4="❌ NO","NO",IF(A4="🟨 MAYBE","MAYBE",""))) -> YES | I4: 3 | J4: Decision updates automatically
A5: ✅ YES | B5: U04 | C5: USER | D5: LMS_ACCESS_REQUEST | E5: Access request submission | F5: =IF(A5="✅ YES","YES",IF(A5="❌ NO","NO",IF(A5="🟨 MAYBE","MAYBE",""))) -> YES | I5: 4 | J5: Use Notes for custom remarks
A6: ❌ NO | B6: U05 | C6: USER | D6: /status | E6: Access status: pending/approved/denied/revoked | F6: =IF(A6="✅ YES","YES",IF(A6="❌ NO","NO",IF(A6="🟨 MAYBE","MAYBE",""))) -> NO
A7: 🟨 MAYBE | B7: U06 | C7: USER | D7: MAIN_MENU | E7: Main LMS navigation | F7: =IF(A7="✅ YES","YES",IF(A7="❌ NO","NO",IF(A7="🟨 MAYBE","MAYBE",""))) -> MAYBE
A8: ✅ YES | B8: U07 | C8: USER | D8: UPSC_MENU | E8: UPSC section | F8: =IF(A8="✅ YES","YES",IF(A8="❌ NO","NO",IF(A8="🟨 MAYBE","MAYBE",""))) -> YES
A9: ✅ YES | B9: U08 | C9: USER | D9: PSC_MENU | E9: State PSC section | F9: =IF(A9="✅ YES","YES",IF(A9="❌ NO","NO",IF(A9="🟨 MAYBE","MAYBE",""))) -> YES
A10: 🟨 MAYBE | B10: U09 | C10: USER | D10: PRELIMS_MAINS | E10: Prelims/Mains section | F10: =IF(A10="✅ YES","YES",IF(A10="❌ NO","NO",IF(A10="🟨 MAYBE","MAYBE",""))) -> MAYBE
A11: 🟨 MAYBE | B11: U10 | C11: USER | D11: SUBJECT_MENU | E11: Subject-specific section | F11: =IF(A11="✅ YES","YES",IF(A11="❌ NO","NO",IF(A11="🟨 MAYBE","MAYBE",""))) -> MAYBE
A12: 🟨 MAYBE | B12: U11 | C12: USER | D12: OPTIONAL_MENU | E12: Optional-subject section | F12: =IF(A12="✅ YES","YES",IF(A12="❌ NO","NO",IF(A12="🟨 MAYBE","MAYBE",""))) -> MAYBE
A13: 🟨 MAYBE | B13: U12 | C13: USER | D13: COURSE_COUNT | E13: Section-wise course count | F13: =IF(A13="✅ YES","YES",IF(A13="❌ NO","NO",IF(A13="🟨 MAYBE","MAYBE",""))) -> MAYBE
A14: 🟨 MAYBE | B14: U13 | C14: USER | D14: /courses | E14: All courses view | F14: =IF(A14="✅ YES","YES",IF(A14="❌ NO","NO",IF(A14="🟨 MAYBE","MAYBE",""))) -> MAYBE
A15: ✅ YES | B15: U14 | C15: USER | D15: /trending | E15: Trending courses | F15: =IF(A15="✅ YES","YES",IF(A15="❌ NO","NO",IF(A15="🟨 MAYBE","MAYBE",""))) -> YES
A16: ✅ YES | B16: U15 | C16: USER | D16: COURSE_DETAIL | E16: Course detail view | F16: =IF(A16="✅ YES","YES",IF(A16="❌ NO","NO",IF(A16="🟨 MAYBE","MAYBE",""))) -> YES
A17: ✅ YES | B17: U16 | C17: USER | D17: BUY_FLOW | E17: Course purchase flow | F17: =IF(A17="✅ YES","YES",IF(A17="❌ NO","NO",IF(A17="🟨 MAYBE","MAYBE",""))) -> YES
... A91: ✅ YES | B91: U90 | C91: USER | D91: USER_SECRET_SCOPE | E91: No backend secret exposure | F91: =IF(A91="✅ YES","YES",IF(A91="❌ NO","NO",IF(A91="🟨 MAYBE","MAYBE",""))) -> YES

Sheet ADMIN
A1: Tick | B1: ID | C1: Role | D1: Command / Code | E1: Feature / Requirement | F1: Decision | G1: Notes | I1: TABLET CONTROL | J1: HOW TO USE
A2: ✅ YES | B2: A01 | C2: ADMIN | D2: /adminhelp | E2: Admin-only command menu | F2: =IF(A2="✅ YES","YES",IF(A2="❌ NO","NO",IF(A2="🟨 MAYBE","MAYBE",""))) -> YES | I2: 1 | J2: Tap TICK cell
A3: ✅ YES | B3: A02 | C3: ADMIN | D3: ADMIN_ALLOWLIST | E3: Backend Admin allow-list | F3: =IF(A3="✅ YES","YES",IF(A3="❌ NO","NO",IF(A3="🟨 MAYBE","MAYBE",""))) -> YES | I3: 2 | J3: Choose ✅ YES / ❌ NO / 🟨 MAYBE
A4: ✅ YES | B4: A03 | C4: ADMIN | D4: /lms_requests | E4: Pending LMS requests | F4: =IF(A4="✅ YES","YES",IF(A4="❌ NO","NO",IF(A4="🟨 MAYBE","MAYBE",""))) -> YES | I4: 3 | J4: Decision updates automatically
A5: ✅ YES | B5: A04 | C5: ADMIN | D5: /lms_approve USER_ID | E5: Approve user | F5: =IF(A5="✅ YES","YES",IF(A5="❌ NO","NO",IF(A5="🟨 MAYBE","MAYBE",""))) -> YES | I5: 4 | J5: Use Notes for custom remarks
A6: ✅ YES | B6: A05 | C6: ADMIN | D6: /lms_deny USER_ID | E6: Deny user | F6: =IF(A6="✅ YES","YES",IF(A6="❌ NO","NO",IF(A6="🟨 MAYBE","MAYBE",""))) -> YES
A7: ✅ YES | B7: A06 | C7: ADMIN | D7: /lms_revoke USER_ID | E7: Revoke LMS access | F7: =IF(A7="✅ YES","YES",IF(A7="❌ NO","NO",IF(A7="🟨 MAYBE","MAYBE",""))) -> YES
A8: ✅ YES | B8: A07 | C8: ADMIN | D8: /lms_grandfather | E8: Grandfather existing customers | F8: =IF(A8="✅ YES","YES",IF(A8="❌ NO","NO",IF(A8="🟨 MAYBE","MAYBE",""))) -> YES
A9: ✅ YES | B9: A08 | C9: ADMIN | D9: /lms_gate | E9: LMS gate ON/OFF | F9: =IF(A9="✅ YES","YES",IF(A9="❌ NO","NO",IF(A9="🟨 MAYBE","MAYBE",""))) -> YES
A10: ✅ YES | B10: A09 | C10: ADMIN | D10: /lockdown | E10: Global kill switch | F10: =IF(A10="✅ YES","YES",IF(A10="❌ NO","NO",IF(A10="🟨 MAYBE","MAYBE",""))) -> YES
A11: ☐ SELECT | B11: A10 | C11: ADMIN | D11: /doubts | E11: Open doubts | F11: =IF(A11="✅ YES","YES",IF(A11="❌ NO","NO",IF(A11="🟨 MAYBE","MAYBE","")))
A12: ✅ YES | B12: A11 | C12: ADMIN | D12: /pending_payments | E12: Pending payment orders | F12: =IF(A12="✅ YES","YES",IF(A12="❌ NO","NO",IF(A12="🟨 MAYBE","MAYBE",""))) -> YES
A13: ☐ SELECT | B13: A12 | C13: ADMIN | D13: /pending | E13: Pending orders | F13: =IF(A13="✅ YES","YES",IF(A13="❌ NO","NO",IF(A13="🟨 MAYBE","MAYBE","")))
A14: ✅ YES | B14: A13 | C14: ADMIN | D14: /approve ORDER_ID | E14: Approve payment | F14: =IF(A14="✅ YES","YES",IF(A14="❌ NO","NO",IF(A14="🟨 MAYBE","MAYBE",""))) -> YES
A15: ✅ YES | B15: A14 | C15: ADMIN | D15: /reject ORDER_ID | E15: Reject payment | F15: =IF(A15="✅ YES","YES",IF(A15="❌ NO","NO",IF(A15="🟨 MAYBE","MAYBE",""))) -> YES
A16: ✅ YES | B16: A15 | C16: ADMIN | D16: /toggle_ai | E16: AI ON/OFF | F16: =IF(A16="✅ YES","YES",IF(A16="❌ NO","NO",IF(A16="🟨 MAYBE","MAYBE",""))) -> YES
A17: ✅ YES | B17: A16 | C17: ADMIN | D17: /offline | E17: Offline AI mode | F17: =IF(A17="✅ YES","YES",IF(A17="❌ NO","NO",IF(A17="🟨 MAYBE","MAYBE",""))) -> YES
... A89: ✅ YES | B89: A88 | C89: ADMIN | D89: ADMIN_DATA_RETENTION | E89: Controlled export/retention management | F89: =IF(A89="✅ YES","YES",IF(A89="❌ NO","NO",IF(A89="🟨 MAYBE","MAYBE",""))) -> YES

Sheet SECURITY
A1: Tick | B1: ID | C1: Role | D1: Command / Code | E1: Feature / Requirement | F1: Decision | G1: Notes | I1: TABLET CONTROL | J1: HOW TO USE
A2: ☐ SELECT | B2: S01 | C2: SHARED | D2: FASTAPI | E2: FastAPI backend | F2: =IF(A2="✅ YES","YES",IF(A2="❌ NO","NO",IF(A2="🟨 MAYBE","MAYBE",""))) | I2: 1 | J2: Tap TICK cell
A3: ☐ SELECT | B3: S02 | C3: SHARED | D3: SAME_LMS_APP | E3: All features in same LMS app | F3: =IF(A3="✅ YES","YES",IF(A3="❌ NO","NO",IF(A3="🟨 MAYBE","MAYBE",""))) | I3: 2 | J3: Choose ✅ YES / ❌ NO / 🟨 MAYBE
A4: ☐ SELECT | B4: S03 | C4: SHARED | D4: TELEGRAM_WEBHOOK | E4: Telegram webhook mode | F4: =IF(A4="✅ YES","YES",IF(A4="❌ NO","NO",IF(A4="🟨 MAYBE","MAYBE",""))) | I4: 3 | J4: Decision updates automatically
A5: ☐ SELECT | B5: S04 | C5: SHARED | D5: api/index.py | E5: Vercel Python entrypoint | F5: =IF(A5="✅ YES","YES",IF(A5="❌ NO","NO",IF(A5="🟨 MAYBE","MAYBE",""))) | I5: 4 | J5: Use Notes for custom remarks
A6: ☐ SELECT | B6: S05 | C6: SHARED | D6: vercel.json | E6: Vercel routing/config | F6: =IF(A6="✅ YES","YES",IF(A6="❌ NO","NO",IF(A6="🟨 MAYBE","MAYBE","")))
A7: ☐ SELECT | B7: S06 | C7: SHARED | D7: /api/cron | E7: Protected scheduler endpoint | F7: =IF(A7="✅ YES","YES",IF(A7="❌ NO","NO",IF(A7="🟨 MAYBE","MAYBE","")))
A8: ☐ SELECT | B8: S07 | C8: SHARED | D8: SERVERLESS_SAFE | E8: Serverless-safe scheduling | F8: =IF(A8="✅ YES","YES",IF(A8="❌ NO","NO",IF(A8="🟨 MAYBE","MAYBE","")))
A9: ☐ SELECT | B9: S08 | C9: SHARED | D9: DB_PERSISTENCE | E9: Persistent database state | F9: =IF(A9="✅ YES","YES",IF(A9="❌ NO","NO",IF(A9="🟨 MAYBE","MAYBE","")))
A10: ☐ SELECT | B10: S09 | C10: SHARED | D10: SQLALCHEMY | E10: SQLAlchemy data layer | F10: =IF(A10="✅ YES","YES",IF(A10="❌ NO","NO",IF(A10="🟨 MAYBE","MAYBE","")))
A11: ☐ SELECT | B11: S10 | C11: SHARED | D11: USERS_TABLE | E11: User records | F11: =IF(A11="✅ YES","YES",IF(A11="❌ NO","NO",IF(A11="🟨 MAYBE","MAYBE","")))
A12: ☐ SELECT | B12: S11 | C12: SHARED | D12: ORDERS_TABLE | E12: Orders | F12: =IF(A12="✅ YES","YES",IF(A12="❌ NO","NO",IF(A12="🟨 MAYBE","MAYBE","")))
A13: ☐ SELECT | B13: S12 | C13: SHARED | D13: COURSES_TABLE | E13: Courses | F13: =IF(A13="✅ YES","YES",IF(A13="❌ NO","NO",IF(A13="🟨 MAYBE","MAYBE","")))
A14: ☐ SELECT | B14: S13 | C14: SHARED | D14: ACCESS_TABLE | E14: User-course access | F14: =IF(A14="✅ YES","YES",IF(A14="❌ NO","NO",IF(A14="🟨 MAYBE","MAYBE","")))
A15: ☐ SELECT | B15: S14 | C15: SHARED | D15: ACTIVITY_TABLE | E15: User activity | F15: =IF(A15="✅ YES","YES",IF(A15="❌ NO","NO",IF(A15="🟨 MAYBE","MAYBE","")))
A16: ☐ SELECT | B16: S15 | C16: SHARED | D16: CONTACT_TABLE | E16: Contact history | F16: =IF(A16="✅ YES","YES",IF(A16="❌ NO","NO",IF(A16="🟨 MAYBE","MAYBE","")))
A17: ☐ SELECT | B17: S16 | C17: SHARED | D17: INBOX_TABLE | E17: Inbox records | F17: =IF(A17="✅ YES","YES",IF(A17="❌ NO","NO",IF(A17="🟨 MAYBE","MAYBE","")))
... A89: ☐ SELECT | B89: S88 | C89: SHARED | D89: ROLLBACK_READY | E89: Rollback-ready deployment | F89: =IF(A89="✅ YES","YES",IF(A89="❌ NO","NO",IF(A89="🟨 MAYBE","MAYBE","")))

Sheet AI
A1: Tick | B1: ID | C1: Role | D1: Command / Code | E1: Feature / Requirement | F1: Decision | G1: Notes | I1: TABLET CONTROL | J1: HOW TO USE
A2: ☐ SELECT | B2: AI01 | C2: AI | D2: PORTAL_ONLY | E2: Portal-specific answers only | F2: =IF(A2="✅ YES","YES",IF(A2="❌ NO","NO",IF(A2="🟨 MAYBE","MAYBE",""))) | I2: 1 | J2: Tap TICK cell
A3: ☐ SELECT | B3: AI02 | C3: AI | D3: QUESTION_SCOPE | E3: Answer exactly the asked question | F3: =IF(A3="✅ YES","YES",IF(A3="❌ NO","NO",IF(A3="🟨 MAYBE","MAYBE",""))) | I3: 2 | J3: Choose ✅ YES / ❌ NO / 🟨 MAYBE
A4: ☐ SELECT | B4: AI03 | C4: AI | D4: NO_IRRELEVANT | E4: No irrelevant information | F4: =IF(A4="✅ YES","YES",IF(A4="❌ NO","NO",IF(A4="🟨 MAYBE","MAYBE",""))) | I4: 3 | J4: Decision updates automatically
A5: ☐ SELECT | B5: AI04 | C5: AI | D5: NO_UNNECESSARY_Q | E5: No unnecessary follow-up questions | F5: =IF(A5="✅ YES","YES",IF(A5="❌ NO","NO",IF(A5="🟨 MAYBE","MAYBE",""))) | I5: 4 | J5: Use Notes for custom remarks
A6: ☐ SELECT | B6: AI05 | C6: AI | D6: LANGUAGE_MATCH | E6: Match user's language | F6: =IF(A6="✅ YES","YES",IF(A6="❌ NO","NO",IF(A6="🟨 MAYBE","MAYBE","")))
A7: ☐ SELECT | B7: AI06 | C7: AI | D7: STYLE_MATCH | E7: Match concise/conversational style | F7: =IF(A7="✅ YES","YES",IF(A7="❌ NO","NO",IF(A7="🟨 MAYBE","MAYBE","")))
A8: ☐ SELECT | B8: AI07 | C8: AI | D8: SHORT_SIMPLE | E8: Short answer for simple query | F8: =IF(A8="✅ YES","YES",IF(A8="❌ NO","NO",IF(A8="🟨 MAYBE","MAYBE","")))
A9: ☐ SELECT | B9: AI08 | C9: AI | D9: DETAILED_WHEN_NEEDED | E9: Detail only when required | F9: =IF(A9="✅ YES","YES",IF(A9="❌ NO","NO",IF(A9="🟨 MAYBE","MAYBE","")))
A10: ☐ SELECT | B10: AI09 | C10: AI | D10: CATALOG_CONTEXT | E10: Use current course catalog | F10: =IF(A10="✅ YES","YES",IF(A10="❌ NO","NO",IF(A10="🟨 MAYBE","MAYBE","")))
A11: ☐ SELECT | B11: AI10 | C11: AI | D11: USER_CONTEXT | E11: Use user's own conversation context | F11: =IF(A11="✅ YES","YES",IF(A11="❌ NO","NO",IF(A11="🟨 MAYBE","MAYBE","")))
A12: ☐ SELECT | B12: AI11 | C12: AI | D12: DURABLE_PROFILE | E12: Use authorized durable student facts | F12: =IF(A12="✅ YES","YES",IF(A12="❌ NO","NO",IF(A12="🟨 MAYBE","MAYBE","")))
A13: ☐ SELECT | B13: AI12 | C13: AI | D13: NO_PRICE_INVENT | E13: Never invent price/access/payment state | F13: =IF(A13="✅ YES","YES",IF(A13="❌ NO","NO",IF(A13="🟨 MAYBE","MAYBE","")))
A14: ☐ SELECT | B14: AI13 | C14: AI | D14: NO_SECRET | E14: Never reveal system prompt/API keys/secrets | F14: =IF(A14="✅ YES","YES",IF(A14="❌ NO","NO",IF(A14="🟨 MAYBE","MAYBE","")))
A15: ☐ SELECT | B15: AI14 | C15: AI | D15: NO_ADMIN_ID | E15: Never reveal Admin ID/account | F15: =IF(A15="✅ YES","YES",IF(A15="❌ NO","NO",IF(A15="🟨 MAYBE","MAYBE","")))
A16: ☐ SELECT | B16: AI15 | C16: AI | D16: NO_HOST_INFO | E16: Never reveal hosting/device info | F16: =IF(A16="✅ YES","YES",IF(A16="❌ NO","NO",IF(A16="🟨 MAYBE","MAYBE","")))
A17: ☐ SELECT | B17: AI16 | C17: AI | D17: NO_OTHER_USER | E17: Never reveal another user's info | F17: =IF(A17="✅ YES","YES",IF(A17="❌ NO","NO",IF(A17="🟨 MAYBE","MAYBE","")))
... A22: ☐ SELECT | B22: AI21 | C22: AI | D22: AI_RATE_POLICY | E22: Usage/rate controls | F22: =IF(A22="✅ YES","YES",IF(A22="❌ NO","NO",IF(A22="🟨 MAYBE","MAYBE","")))

Sheet MASTER
A1: TICK | B1: Role | C1: ID | D1: Command / Code | E1: Feature / Requirement | F1: Decision | G1: NOTES | I1: TABLET CONTROL | J1: HOW TO USE
A2: ☐ SELECT | B2: USER | C2: U01 | D2: /start | E2: Welcome/menu open | F2: =IF(A2="✅ YES","YES",IF(A2="❌ NO","NO",IF(A2="🟨 MAYBE","MAYBE",""))) | I2: 1 | J2: Tap TICK cell
A3: ☐ SELECT | B3: USER | C3: U02 | D3: /start ref_ID | E3: Referral/deep-link tracking | F3: =IF(A3="✅ YES","YES",IF(A3="❌ NO","NO",IF(A3="🟨 MAYBE","MAYBE",""))) | I3: 2 | J3: Choose ✅ YES / ❌ NO / 🟨 MAYBE
A4: ☐ SELECT | B4: USER | C4: U03 | D4: BACKUP_CHANNEL_CHECK | E4: Backup-channel / join verification gate | F4: =IF(A4="✅ YES","YES",IF(A4="❌ NO","NO",IF(A4="🟨 MAYBE","MAYBE",""))) | I4: 3 | J4: Decision updates automatically
A5: ☐ SELECT | B5: USER | C5: U04 | D5: LMS_ACCESS_REQUEST | E5: Access request submission | F5: =IF(A5="✅ YES","YES",IF(A5="❌ NO","NO",IF(A5="🟨 MAYBE","MAYBE",""))) | I5: 4 | J5: Use Notes for custom remarks
A6: ☐ SELECT | B6: USER | C6: U05 | D6: /status | E6: Access status: pending/approved/denied/revoked | F6: =IF(A6="✅ YES","YES",IF(A6="❌ NO","NO",IF(A6="🟨 MAYBE","MAYBE","")))
A7: ☐ SELECT | B7: USER | C7: U06 | D7: MAIN_MENU | E7: Main LMS navigation | F7: =IF(A7="✅ YES","YES",IF(A7="❌ NO","NO",IF(A7="🟨 MAYBE","MAYBE","")))
A8: ☐ SELECT | B8: USER | C8: U07 | D8: UPSC_MENU | E8: UPSC section | F8: =IF(A8="✅ YES","YES",IF(A8="❌ NO","NO",IF(A8="🟨 MAYBE","MAYBE","")))
A9: ☐ SELECT | B9: USER | C9: U08 | D9: PSC_MENU | E9: State PSC section | F9: =IF(A9="✅ YES","YES",IF(A9="❌ NO","NO",IF(A9="🟨 MAYBE","MAYBE","")))
A10: ☐ SELECT | B10: USER | C10: U09 | D10: PRELIMS_MAINS | E10: Prelims/Mains section | F10: =IF(A10="✅ YES","YES",IF(A10="❌ NO","NO",IF(A10="🟨 MAYBE","MAYBE","")))
A11: ☐ SELECT | B11: USER | C11: U10 | D11: SUBJECT_MENU | E11: Subject-specific section | F11: =IF(A11="✅ YES","YES",IF(A11="❌ NO","NO",IF(A11="🟨 MAYBE","MAYBE","")))
A12: ☐ SELECT | B12: USER | C12: U11 | D12: OPTIONAL_MENU | E12: Optional-subject section | F12: =IF(A12="✅ YES","YES",IF(A12="❌ NO","NO",IF(A12="🟨 MAYBE","MAYBE","")))
A13: ☐ SELECT | B13: USER | C13: U12 | D13: COURSE_COUNT | E13: Section-wise course count | F13: =IF(A13="✅ YES","YES",IF(A13="❌ NO","NO",IF(A13="🟨 MAYBE","MAYBE","")))
A14: ☐ SELECT | B14: USER | C14: U13 | D14: /courses | E14: All courses view | F14: =IF(A14="✅ YES","YES",IF(A14="❌ NO","NO",IF(A14="🟨 MAYBE","MAYBE","")))
A15: ☐ SELECT | B15: USER | C15: U14 | D15: /trending | E15: Trending courses | F15: =IF(A15="✅ YES","YES",IF(A15="❌ NO","NO",IF(A15="🟨 MAYBE","MAYBE","")))
A16: ☐ SELECT | B16: USER | C16: U15 | D16: COURSE_DETAIL | E16: Course detail view | F16: =IF(A16="✅ YES","YES",IF(A16="❌ NO","NO",IF(A16="🟨 MAYBE","MAYBE","")))
A17: ☐ SELECT | B17: USER | C17: U16 | D17: BUY_FLOW | E17: Course purchase flow | F17: =IF(A17="✅ YES","YES",IF(A17="❌ NO","NO",IF(A17="🟨 MAYBE","MAYBE","")))
... A288: ☐ SELECT | B288: AI | C288: AI21 | D288: AI_RATE_POLICY | E288: Usage/rate controls | F288: =IF(A288="✅ YES","YES",IF(A288="❌ NO","NO",IF(A288="🟨 MAYBE","MAYBE","")))

Sheet SUMMARY
A1: LMS A–Z FEATURE CHECKLIST — TABLET CONTROL
A2: Category | B2: Total | C2: YES | D2: NO | E2: MAYBE
A3: USER | B3: 90 | C3: =_xlfn.COUNTIFS(MASTER!B:B,A3,MASTER!F:F,"YES") -> 0 | D3: =_xlfn.COUNTIFS(MASTER!B:B,A3,MASTER!F:F,"NO") -> 0 | E3: =_xlfn.COUNTIFS(MASTER!B:B,A3,MASTER!F:F,"MAYBE") -> 0
A4: ADMIN | B4: 88 | C4: =_xlfn.COUNTIFS(MASTER!B:B,A4,MASTER!F:F,"YES") -> 0 | D4: =_xlfn.COUNTIFS(MASTER!B:B,A4,MASTER!F:F,"NO") -> 0 | E4: =_xlfn.COUNTIFS(MASTER!B:B,A4,MASTER!F:F,"MAYBE") -> 0
A5: SECURITY | B5: 88 | C5: =_xlfn.COUNTIFS(MASTER!B:B,A5,MASTER!F:F,"YES") -> 0 | D5: =_xlfn.COUNTIFS(MASTER!B:B,A5,MASTER!F:F,"NO") -> 0 | E5: =_xlfn.COUNTIFS(MASTER!B:B,A5,MASTER!F:F,"MAYBE") -> 0
A6: AI | B6: 21 | C6: =_xlfn.COUNTIFS(MASTER!B:B,A6,MASTER!F:F,"YES") -> 0 | D6: =_xlfn.COUNTIFS(MASTER!B:B,A6,MASTER!F:F,"NO") -> 0 | E6: =_xlfn.COUNTIFS(MASTER!B:B,A6,MASTER!F:F,"MAYBE") -> 0
A7: TOTAL | B7: 287 | C7: =SUM(C3:C6) -> 0 | D7: =SUM(D3:D6) -> 0 | E7: =SUM(E3:E6) -> 0
A8: Selected (YES) | C8: =C7 -> 0
A9: Remaining (NO/MAYBE) | C9: =D7+E7 -> 0
